MANIFEST.in
README.rst
requirements.txt
setup.cfg
setup.py
APImetrics.egg-info/PKG-INFO
APImetrics.egg-info/SOURCES.txt
APImetrics.egg-info/dependency_links.txt
APImetrics.egg-info/entry_points.txt
APImetrics.egg-info/requires.txt
APImetrics.egg-info/top_level.txt
APImetrics.egg-info/zip-safe
apimetrics/__init__.py
apimetrics/__main__.py
apimetrics/api.py
apimetrics/cli.py
apimetrics/command_line.py
apimetrics/errors.py
apimetrics/scripts/__init__.py
apimetrics/scripts/delete_deployments.py
apimetrics/scripts/delete_deployments_workflows.py
apimetrics/scripts/deploy_all_apis.py
apimetrics/scripts/deploy_all_workflows.py
apimetrics/scripts/spread_out_deployments.py