Metadata-Version: 1.1
Name: APImetrics
Version: 0.2.2
Summary: APImetrics Client
Home-page: http://apimetrics.io/
Author: Nick Denny
Author-email: nick@apimetrics.io
License: License :: OSI Approved :: Apache Software License
Download-URL: https://github.com/APImetrics/APImetrics-Python-Client/archive/v0.2.2.tar.gz
Keywords: api http monitoring test apimetrics
Platform: UNKNOWN
Classifier: Development Status :: 4 - Beta
Classifier: License :: OSI Approved :: Apache Software License
Classifier: Intended Audience :: Developers
Classifier: Intended Audience :: System Administrators
Classifier: Topic :: Software Development :: Testing
Classifier: Topic :: System :: Networking :: Monitoring
Classifier: Topic :: Utilities
Classifier: Programming Language :: Python
Classifier: Programming Language :: Python :: 2
Classifier: Programming Language :: Python :: 2.7
Classifier: Programming Language :: Python :: 3
Classifier: Programming Language :: Python :: 3.3
Classifier: Programming Language :: Python :: 3.4
Classifier: Programming Language :: Python :: 3.5
Classifier: Programming Language :: Python :: 3.6
Classifier: Environment :: Console
Classifier: Operating System :: POSIX
